[
  {
    "date": "2025-11-17",
    "startTime": "09:00",
    "endTime": "10:00",
    "color": "#3b82f6",
    "title": "Team Standup Meeting",
    "category": "meeting",
    "priority": "high",
    "description": "Daily team synchronization and progress updates",
    "recurring": "none"
  },
  {
    "date": "2025-11-17",
    "startTime": "09:30",
    "endTime": "10:30",
    "color": "#ef4444",
    "title": "Conflict Example: Overlapping Meeting",
    "category": "meeting",
    "priority": "high",
    "description": "This event conflicts with the standup meeting - demonstrating conflict detection",
    "recurring": "none"
  },
  {
    "date": "2025-11-17",
    "startTime": "11:00",
    "endTime": "12:30",
    "color": "#10b981",
    "title": "Client Presentation",
    "category": "work",
    "priority": "high",
    "description": "Q4 results presentation to key stakeholders",
    "recurring": "none"
  },
  {
    "date": "2025-11-17",
    "startTime": "14:00",
    "endTime": "15:00",
    "color": "#f59e0b",
    "title": "Code Review Session",
    "category": "work",
    "priority": "medium",
    "description": "Review pull requests and provide feedback",
    "recurring": "none"
  },
  {
    "date": "2025-11-18",
    "startTime": "10:00",
    "endTime": "11:30",
    "color": "#8b5cf6",
    "title": "Sprint Planning",
    "category": "meeting",
    "priority": "high",
    "description": "Plan tasks and user stories for the upcoming sprint",
    "recurring": "none"
  },
  {
    "date": "2025-11-18",
    "startTime": "13:00",
    "endTime": "14:00",
    "color": "#ec4899",
    "title": "One-on-One with Manager",
    "category": "meeting",
    "priority": "medium",
    "description": "Weekly sync with direct manager",
    "recurring": "none"
  },
  {
    "date": "2025-11-18",
    "startTime": "15:00",
    "endTime": "16:00",
    "color": "#06b6d4",
    "title": "Design Review",
    "category": "work",
    "priority": "medium",
    "description": "Review new UI/UX designs for the dashboard",
    "recurring": "none"
  },
  {
    "date": "2025-11-19",
    "startTime": "09:00",
    "endTime": "10:00",
    "color": "#3b82f6",
    "title": "Team Standup",
    "category": "meeting",
    "priority": "high",
    "description": "Daily standup meeting",
    "recurring": "none"
  },
  {
    "date": "2025-11-19",
    "startTime": "11:00",
    "endTime": "12:00",
    "color": "#f97316",
    "title": "Project Deadline",
    "category": "deadline",
    "priority": "high",
    "description": "Final submission for Q4 project deliverables",
    "recurring": "none"
  },
  {
    "date": "2025-11-19",
    "startTime": "14:00",
    "endTime": "16:00",
    "color": "#10b981",
    "title": "Workshop: Best Practices",
    "category": "work",
    "priority": "medium",
    "description": "Learn about coding best practices and design patterns",
    "recurring": "none"
  },
  {
    "date": "2025-11-20",
    "startTime": "10:00",
    "endTime": "11:00",
    "color": "#8b5cf6",
    "title": "Architecture Discussion",
    "category": "meeting",
    "priority": "high",
    "description": "Discuss system architecture for new microservice",
    "recurring": "none"
  },
  {
    "date": "2025-11-20",
    "startTime": "12:00",
    "endTime": "13:00",
    "color": "#ec4899",
    "title": "Lunch & Learn",
    "category": "personal",
    "priority": "low",
    "description": "Team lunch with knowledge sharing session",
    "recurring": "none"
  },
  {
    "date": "2025-11-20",
    "startTime": "15:00",
    "endTime": "16:30",
    "color": "#f59e0b",
    "title": "Customer Feedback Review",
    "category": "work",
    "priority": "medium",
    "description": "Analyze customer feedback and plan improvements",
    "recurring": "none"
  },
  {
    "date": "2025-11-21",
    "startTime": "09:00",
    "endTime": "10:00",
    "color": "#3b82f6",
    "title": "Daily Standup",
    "category": "meeting",
    "priority": "high",
    "description": "Daily team sync",
    "recurring": "none"
  },
  {
    "date": "2025-11-21",
    "startTime": "10:30",
    "endTime": "12:00",
    "color": "#ef4444",
    "title": "Incident Post-Mortem",
    "category": "meeting",
    "priority": "high",
    "description": "Review last week's production incident",
    "recurring": "none"
  },
  {
    "date": "2025-11-21",
    "startTime": "14:00",
    "endTime": "15:00",
    "color": "#06b6d4",
    "title": "Team Building Activity",
    "category": "personal",
    "priority": "low",
    "description": "Virtual team building games and activities",
    "recurring": "none"
  },
  {
    "date": "2025-11-22",
    "startTime": "10:00",
    "endTime": "11:30",
    "color": "#10b981",
    "title": "Product Demo",
    "category": "work",
    "priority": "high",
    "description": "Demonstrate new features to stakeholders",
    "recurring": "none"
  },
  {
    "date": "2025-11-22",
    "startTime": "13:00",
    "endTime": "14:00",
    "color": "#f97316",
    "title": "Documentation Review",
    "category": "work",
    "priority": "low",
    "description": "Review and update technical documentation",
    "recurring": "none"
  },
  {
    "date": "2025-11-24",
    "startTime": "09:00",
    "endTime": "10:30",
    "color": "#8b5cf6",
    "title": "Weekly Planning Meeting",
    "category": "meeting",
    "priority": "high",
    "description": "Plan objectives and priorities for the week",
    "recurring": "none"
  },
  {
    "date": "2025-11-24",
    "startTime": "11:00",
    "endTime": "12:00",
    "color": "#ec4899",
    "title": "Reminder: Submit Timesheet",
    "category": "reminder",
    "priority": "medium",
    "description": "Don't forget to submit weekly timesheet",
    "recurring": "none"
  },
  {
    "date": "2025-11-25",
    "startTime": "14:00",
    "endTime": "15:30",
    "color": "#3b82f6",
    "title": "Retrospective Meeting",
    "category": "meeting",
    "priority": "high",
    "description": "Sprint retrospective - what went well and what can improve",
    "recurring": "none"
  },
  {
    "date": "2025-11-25",
    "startTime": "16:00",
    "endTime": "17:00",
    "color": "#f59e0b",
    "title": "Security Training",
    "category": "work",
    "priority": "medium",
    "description": "Mandatory security awareness training",
    "recurring": "none"
  },
  {
    "date": "2025-11-26",
    "startTime": "10:00",
    "endTime": "11:00",
    "color": "#10b981",
    "title": "Performance Review Prep",
    "category": "personal",
    "priority": "high",
    "description": "Prepare materials for annual performance review",
    "recurring": "none"
  },
  {
    "date": "2025-11-26",
    "startTime": "15:00",
    "endTime": "16:00",
    "color": "#06b6d4",
    "title": "Technical Interview",
    "category": "meeting",
    "priority": "medium",
    "description": "Interview candidate for senior developer position",
    "recurring": "none"
  },
  {
    "date": "2025-11-27",
    "startTime": "09:00",
    "endTime": "10:00",
    "color": "#ef4444",
    "title": "Budget Review Deadline",
    "category": "deadline",
    "priority": "high",
    "description": "Submit department budget for next quarter",
    "recurring": "none"
  },
  {
    "date": "2025-11-27",
    "startTime": "11:00",
    "endTime": "12:00",
    "color": "#8b5cf6",
    "title": "All-Hands Meeting",
    "category": "meeting",
    "priority": "medium",
    "description": "Company-wide monthly all-hands meeting",
    "recurring": "none"
  },
  {
    "date": "2025-11-28",
    "startTime": "13:00",
    "endTime": "14:00",
    "color": "#ec4899",
    "title": "Team Lunch",
    "category": "personal",
    "priority": "low",
    "description": "Casual team lunch at new restaurant",
    "recurring": "none"
  },
  {
    "date": "2025-11-29",
    "startTime": "10:00",
    "endTime": "11:00",
    "color": "#f97316",
    "title": "Month-End Report",
    "category": "deadline",
    "priority": "high",
    "description": "Complete and submit monthly status report",
    "recurring": "none"
  },
  {
    "date": "2025-11-29",
    "startTime": "14:00",
    "endTime": "15:00",
    "color": "#3b82f6",
    "title": "Celebration: Project Launch",
    "category": "personal",
    "priority": "low",
    "description": "Celebrate successful project launch with team",
    "recurring": "none"
  }
]
